test_novaroma_1234/__init__.py
test_novaroma_1234-0.1.0.dist-info/METADATA
test_novaroma_1234-0.1.0.dist-info/WHEEL
test_novaroma_1234-0.1.0.dist-info/entry_points.txt
test_novaroma_1234-0.1.0.dist-info/RECORD
