Metadata-Version: 2.4
Name: test-novaroma-1234
Version: 0.1.0
Summary: objeto de teste
Author-email: Gutto <guttolaudie@gmail.com>
Requires-Python: >=3.11
Requires-Dist: numpy>=2.2.5
